[
  {
    "id": "55292ed7-896c-41c8-a231-d31cca7ac877",
    "name": "Holy Trinity Cathedral",
    "imageUrl": "https://upload.wikimedia.org/wikipedia/commons/e/ec/Holy_Trinity_Cathedral%2C_Addis_Ababa_%283434312871%29.jpg",
    "sourcePageUrl": "https://commons.wikimedia.org/wiki/File:Holy_Trinity_Cathedral,_Addis_Ababa_(3434312871).jpg",
    "source": "wikimedia"
  },
  {
    "id": "b893f013-545c-481b-bf72-984d0fad98d4",
    "name": "Unity Park",
    "imageUrl": "https://upload.wikimedia.org/wikipedia/commons/6/6b/Unity_ParkU.jpg",
    "sourcePageUrl": "https://commons.wikimedia.org/wiki/File:Unity_ParkU.jpg",
    "source": "wikimedia"
  },
  {
    "id": "01dc98e3-aa22-4c97-9cb5-fabd8ae9f263",
    "name": "Menelik II Palace",
    "imageUrl": "https://upload.wikimedia.org/wikipedia/commons/3/3d/Palacio_de_Menelik_II%2C_Ad%C3%ADs_Abeba%2C_Etiop%C3%ADa%2C_2024-01-19%2C_DD_03.jpg",
    "sourcePageUrl": "https://commons.wikimedia.org/wiki/File:Palacio_de_Menelik_II,_Ad%C3%ADs_Abeba,_Etiop%C3%ADa,_2024-01-19,_DD_03.jpg",
    "source": "wikimedia"
  },
  {
    "id": "5e4a5cc1-d3dd-4c5f-bba1-e36a9f7701e6",
    "name": "Red Terror Martyrs Memorial Museum",
    "imageUrl": "https://upload.wikimedia.org/wikipedia/commons/8/8d/Red_Terror_Martyrs%27_Memorial_Museum_in_Addis_Ababa_02.jpg",
    "sourcePageUrl": "https://commons.wikimedia.org/wiki/File:Red_Terror_Martyrs%27_Memorial_Museum_in_Addis_Ababa_02.jpg",
    "source": "wikimedia"
  },
  {
    "id": "69a105ed-0739-4f8f-aaf6-460e74ef6d22",
    "name": "Ethnological Museum (Addis Ababa University)",
    "imageUrl": "https://upload.wikimedia.org/wikipedia/commons/c/c3/Facade_and_entrance_of_the_Ethnological_Museum%2C_Addis_Ababa_%2826430577063%29.jpg",
    "sourcePageUrl": "https://commons.wikimedia.org/wiki/File:Facade_and_entrance_of_the_Ethnological_Museum,_Addis_Ababa_(26430577063).jpg",
    "source": "wikimedia"
  },
  {
    "id": "3ff755aa-0980-4d66-8ff1-fca02750ceae",
    "name": "Entoto Natural Park",
    "imageUrl": "https://commons.wikimedia.org/wiki/Special:FilePath/Addis_Ababa_from_Entoto_Mountains.jpg",
    "sourcePageUrl": "https://commons.wikimedia.org/wiki/File:Addis_Ababa_from_Entoto_Mountains.jpg",
    "source": "wikimedia"
  },
  {
    "id": "a9713e6b-b379-44d7-bec8-b0766c299b06",
    "name": "Sheger Riverside Park",
    "imageUrl": "https://commons.wikimedia.org/wiki/Special:FilePath/AddisView.jpg",
    "sourcePageUrl": "https://commons.wikimedia.org/wiki/File:AddisView.jpg",
    "source": "wikimedia"
  },
  {
    "id": "bbe775c9-6acf-40e9-8a2b-28c27aff9606",
    "name": "Friendship Park",
    "imageUrl": "https://upload.wikimedia.org/wikipedia/commons/6/6e/AddisView.jpg",
    "sourcePageUrl": "https://commons.wikimedia.org/wiki/File:AddisView.jpg",
    "source": "wikimedia"
  },
  {
    "id": "e6c552e0-51ae-4f29-bc7d-2d959e912d42",
    "name": "Addis Ababa Museum",
    "imageUrl": "https://commons.wikimedia.org/wiki/Special:FilePath/Addis_Ababa_Museum_(11243068196).jpg",
    "sourcePageUrl": "https://commons.wikimedia.org/wiki/File:Addis_Ababa_Museum_(11243068196).jpg",
    "source": "wikimedia"
  },
  {
    "id": "5298080e-edb9-467f-820b-c697b866572c",
    "name": "Africa Hall (UNECA)",
    "imageUrl": "https://upload.wikimedia.org/wikipedia/en/a/ac/African_Hall_Addis_Abeba.jpg",
    "sourcePageUrl": "https://en.wikipedia.org/wiki/File:African_Hall_Addis_Abeba.jpg",
    "source": "wikimedia"
  },
  {
    "id": "a8cfc05a-fa93-433f-9d56-902d403d3d38",
    "name": "St George Cathedral",
    "imageUrl": "https://upload.wikimedia.org/wikipedia/commons/b/b7/Katedr%C3%A1la_sv._Ji%C5%99%C3%AD.jpg",
    "sourcePageUrl": "https://commons.wikimedia.org/wiki/File:Katedr%C3%A1la_sv._Ji%C5%99%C3%AD.jpg",
    "source": "wikimedia"
  },
  {
    "id": "6e20c408-5158-4c2b-8043-f2ab48f948a3",
    "name": "Yekatit 12 Monument",
    "imageUrl": "https://commons.wikimedia.org/wiki/Special:FilePath/Yekatit_12_Monument_Addis_Ababa.jpg",
    "sourcePageUrl": "https://commons.wikimedia.org/wiki/File:Yekatit_12_Monument_Addis_Ababa.jpg",
    "source": "wikimedia"
  },
  {
    "id": "a41f8bec-ffa5-4879-a201-e1a018b77074",
    "name": "Entoto Maryam Church area",
    "imageUrl": "https://commons.wikimedia.org/wiki/Special:FilePath/Iglesia_de_Entoto_Maryam,_Adís_Abeba,_Etiopía,_2024-01-19,_DD_01.jpg",
    "sourcePageUrl": "https://commons.wikimedia.org/wiki/File:Iglesia_de_Entoto_Maryam,_Adís_Abeba,_Etiopía,_2024-01-19,_DD_01.jpg",
    "source": "wikimedia"
  },
  {
    "id": "1b8cc80b-c760-42d6-842b-eb2cfdcbb885",
    "name": "Mount Entoto viewpoint",
    "imageUrl": "https://commons.wikimedia.org/wiki/Special:FilePath/Addis_Ababa_from_Entoto_Mountains.jpg",
    "sourcePageUrl": "https://commons.wikimedia.org/wiki/File:Addis_Ababa_from_Entoto_Mountains.jpg",
    "source": "wikimedia"
  },
  {
    "id": "b02f6729-f491-4cce-b03a-f79d216e51bf",
    "name": "Addis Ababa Lion Zoo",
    "imageUrl": "https://commons.wikimedia.org/wiki/Special:FilePath/Lion_zoo_Addis_Ababa_3.jpg",
    "sourcePageUrl": "https://commons.wikimedia.org/wiki/File:Lion_zoo_Addis_Ababa_3.jpg",
    "source": "wikimedia"
  },
  {
    "id": "28fdff2f-042b-4a84-ad61-8507d784d62c",
    "name": "Gulele Botanical Garden",
    "imageUrl": "https://thereportermagazines.com/wp-content/uploads/2024/05/1K1A0041-scaled.jpg",
    "sourcePageUrl": "https://thereportermagazines.com/2747/",
    "source": "official"
  },
  {
    "id": "abe23c46-3ee8-421a-bfe6-a56197efdd75",
    "name": "Unity Park Gardens",
    "imageUrl": "https://commons.wikimedia.org/wiki/Special:FilePath/Unity_Park_Addis_Ababa_Ethiopia_1.jpg",
    "sourcePageUrl": "https://commons.wikimedia.org/wiki/File:Unity_Park_Addis_Ababa_Ethiopia_1.jpg",
    "source": "wikimedia"
  },
  {
    "id": "bc084d3e-d053-4bef-b040-5b0b7e0717ba",
    "name": "Merkato Market",
    "imageUrl": "https://commons.wikimedia.org/wiki/Special:FilePath/Addis_Mercato,_Adís_Abeba,_Etiopía,_2024-01-19,_DD_27.jpg",
    "sourcePageUrl": "https://commons.wikimedia.org/wiki/File:Addis_Mercato,_Adís_Abeba,_Etiopía,_2024-01-19,_DD_27.jpg",
    "source": "wikimedia"
  },
  {
    "id": "5dd786b9-a7e0-485c-a10a-31193c36f70f",
    "name": "Shola Market",
    "imageUrl": "https://commons.wikimedia.org/wiki/Special:FilePath/Addis_abeba,_mercato_sholla,_01.jpg",
    "sourcePageUrl": "https://commons.wikimedia.org/wiki/File:Addis_abeba,_mercato_sholla,_01.jpg",
    "source": "wikimedia"
  },
  {
    "id": "8d060891-4515-4709-9166-b9ffa7d259e8",
    "name": "Piazza Market Area",
    "imageUrl": "https://commons.wikimedia.org/wiki/Special:FilePath/Street_Scene_-_Piazza_District_-_Addis_Ababa_-_Ethiopia_(8659539441).jpg",
    "sourcePageUrl": "https://commons.wikimedia.org/wiki/File:Street_Scene_-_Piazza_District_-_Addis_Ababa_-_Ethiopia_(8659539441).jpg",
    "source": "wikimedia"
  },
  {
    "id": "15a78687-228f-4483-a312-1b7964d2a11a",
    "name": "Shiromeda Market",
    "imageUrl": "https://commons.wikimedia.org/wiki/Special:FilePath/Shiro_Meda_clothing_market.jpg",
    "sourcePageUrl": "https://commons.wikimedia.org/wiki/File:Shiro_Meda_clothing_market.jpg",
    "source": "wikimedia"
  },
  {
    "id": "76ed8ba7-b890-4ffe-b642-bc5aca5abb36",
    "name": "Tomoca Coffee",
    "imageUrl": "https://commons.wikimedia.org/wiki/Special:FilePath/Tomoca_Coffee_House,_Addis_(12585688875).jpg",
    "sourcePageUrl": "https://commons.wikimedia.org/wiki/File:Tomoca_Coffee_House,_Addis_(12585688875).jpg",
    "source": "wikimedia"
  },
  {
    "id": "94582738-ace3-4c76-a4fa-a9a3d82cd279",
    "name": "Kaldi's Coffee (Bole branch)",
    "imageUrl": "https://dynamic-media-cdn.tripadvisor.com/media/photo-o/0f/bf/be/bb/kaldi-s-coffee-shop.jpg?w=900&h=500&s=1",
    "sourcePageUrl": "https://www.tripadvisor.com/Restaurant_Review-g293791-d1214049-Reviews-Kaldi_s_Coffee-Addis_Ababa.html",
    "source": "official"
  },
  {
    "id": "07f95fe3-1d4d-4704-a51f-3b9b92b8b5ff",
    "name": "Kaldi's Coffee (Kazanchis)",
    "imageUrl": "https://dynamic-media-cdn.tripadvisor.com/media/photo-o/0f/bf/be/bb/kaldi-s-coffee-shop.jpg?w=900&h=500&s=1",
    "sourcePageUrl": "https://www.tripadvisor.com/Restaurant_Review-g293791-d1214049-Reviews-Kaldi_s_Coffee-Addis_Ababa.html",
    "source": "official"
  },
  {
    "id": "dcf61b97-7e82-49e9-a505-b56ef29531cd",
    "name": "Garden of Coffee",
    "imageUrl": "https://cdn.shopify.com/s/files/1/1317/1755/files/20190112_063304.jpg?v=1572943275",
    "sourcePageUrl": "https://gardenofcoffee.com/pages/cafe-roastery-sar-bet-jfk-building",
    "source": "official"
  },
  {
    "id": "b93a5ed4-97bd-4fa7-8c5c-ac2041e1055f",
    "name": "Alem Bunna",
    "imageUrl": "https://media-cdn.tripadvisor.com/media/photo-o/02/69/07/9c/alem-bunna.jpg",
    "sourcePageUrl": "https://media-cdn.tripadvisor.com/media/photo-o/02/69/07/9c/alem-bunna.jpg",
    "source": "official"
  },
  {
    "id": "04ecbc66-19da-4c15-b1f5-e2e21078d74d",
    "name": "Galani Coffee",
    "imageUrl": "https://static.wixstatic.com/media/81af6121f84c41a5b4391d7d37fce12a.png/v1/fill/w_1200,h_800,al_c,q_90/81af6121f84c41a5b4391d7d37fce12a.png",
    "sourcePageUrl": "https://www.galanicoffee.com/",
    "source": "official"
  },
  {
    "id": "eda3476e-a143-497d-8185-135169dd669a",
    "name": "Yod Abyssinia Cultural Restaurant",
    "imageUrl": "https://yodabyssiniaplc.com/wp-content/uploads/2021/05/yod-exterior.jpg",
    "sourcePageUrl": "https://yodabyssiniaplc.com/",
    "source": "official"
  },
  {
    "id": "f2c31d57-12d0-4082-8aac-d1ac47be2872",
    "name": "Kategna Restaurant",
    "imageUrl": "https://static.wixstatic.com/media/9e3191_d0aa3adddcba44ffbeb97947dd7b1e4a~mv2_d_6000_4000_s_4_2.jpg",
    "sourcePageUrl": "https://static.wixstatic.com/media/9e3191_d0aa3adddcba44ffbeb97947dd7b1e4a~mv2_d_6000_4000_s_4_2.jpg",
    "source": "official"
  },
  {
    "id": "0473949f-1d6c-45fe-a1cf-327fec892bc7",
    "name": "Castelli Restaurant",
    "imageUrl": "https://media-cdn.tripadvisor.com/media/photo-o/00/ce/50/8a/delicious.jpg",
    "sourcePageUrl": "https://media-cdn.tripadvisor.com/media/photo-o/00/ce/50/8a/delicious.jpg",
    "source": "official"
  },
  {
    "id": "55758457-2ee2-4e96-b80a-1922c6828ad7",
    "name": "Sheraton Addis",
    "imageUrl": "https://cache.marriott.com/content/dam/marriott-renditions/ADDLC/addlc-exterior-7436-hor-feat.jpg?output-quality=70&interpolation=progressive-bilinear&downsize=1920px:*",
    "sourcePageUrl": "https://www.marriott.com/en-us/hotels/addlc-sheraton-addis-a-luxury-collection-hotel-addis-ababa/overview/",
    "source": "official"
  },
  {
    "id": "0483a594-e04c-483e-a75b-36b5385d6d34",
    "name": "Hyatt Regency Addis Ababa",
    "imageUrl": "https://assets.hyatt.com/content/dam/hyatt/hyattdam/images/2019/02/20/0822/Hyatt-Regency-Addis-Ababa-P007-Recreational-Swimming-Pool.jpg/Hyatt-Regency-Addis-Ababa-P007-Recreational-Swimming-Pool.16x9.jpg?imwidth=1920",
    "sourcePageUrl": "https://assets.hyatt.com/content/dam/hyatt/hyattdam/images/2019/02/20/0822/Hyatt-Regency-Addis-Ababa-P007-Recreational-Swimming-Pool.jpg/Hyatt-Regency-Addis-Ababa-P007-Recreational-Swimming-Pool.16x9.jpg?imwidth=1920",
    "source": "official"
  },
  {
    "id": "2babe647-79db-46d5-8ec9-0be1a3e3dcde",
    "name": "Radisson Blu Addis Ababa",
    "imageUrl": "https://visitethiopia.et/uploads/0000/1/2024/04/16/r.jpg",
    "sourcePageUrl": "https://visitethiopia.et/hotel/radisson-blu-hotel-addis-ababa",
    "source": "official"
  },
  {
    "id": "15f1f8aa-f5a2-484b-9f46-612ff2c2a157",
    "name": "Capital Hotel & Spa",
    "imageUrl": "https://cf.bstatic.com/xdata/images/hotel/max1024x768/63285961.jpg?k=b690c02f5f6a54aa1f626d02f259b329ac77a74d9d2d76b54eb97e2bb8241589&o=",
    "sourcePageUrl": "https://www.booking.com/hotel/et/capital-and-spa.html",
    "source": "official"
  },
  {
    "id": "8a5f9ab7-e183-401e-bad6-e7a40834b32f",
    "name": "Marriott Executive Apartments Addis Ababa",
    "imageUrl": "https://cache.marriott.com/content/dam/marriott-digital/er/emea/hws/a/adder/en_us/photo/unlimited/assets/adder-exterior-0001.jpg",
    "sourcePageUrl": "https://cache.marriott.com/content/dam/marriott-digital/er/emea/hws/a/adder/en_us/photo/unlimited/assets/adder-exterior-0001.jpg",
    "source": "official"
  },
  {
    "id": "51efc284-9cc3-4b54-857c-b73acb4fa5c8",
    "name": "Golden Tulip Addis Ababa",
    "imageUrl": "https://upload.wikimedia.org/wikipedia/commons/a/a7/Golden_Tulip_Addis_Ababa_Hotel_External.jpg",
    "sourcePageUrl": "https://commons.wikimedia.org/wiki/File:Golden_Tulip_Addis_Ababa_Hotel_External.jpg",
    "source": "wikimedia"
  },
  {
    "id": "80c2fb2e-a2b8-43eb-82c1-3627d892e13d",
    "name": "Best Western Plus Addis Ababa",
    "imageUrl": "https://ik.imgkit.net/3vlqs5axxjf/external/https://media.iceportal.com/102413/photos/84578621_XL.jpg?tr=w-1200%2Cfo-auto",
    "sourcePageUrl": "https://www.travelweekly.com/Hotels/Addis-Ababa-Ethiopia/Best-Western-Plus-Addis-Ababa-p56055808",
    "source": "official"
  },
  {
    "id": "cee4b837-89e0-498a-bf19-01d55c6cb343",
    "name": "Jupiter International Hotel",
    "imageUrl": "https://webbox.imgix.net/images/mvqnaiwlzbipmgce/8354285c-0cf5-4895-85f4-1d94819f3e40.jpg?auto=format,compress&fit=crop&crop=entropy&w=750&h=600",
    "sourcePageUrl": "https://www.jupiterinternationalhotel.com/",
    "source": "official"
  },
  {
    "id": "7352b79a-c758-45d1-a438-a43ba11d3b27",
    "name": "Harmony Hotel Addis Ababa",
    "imageUrl": "https://pix8.agoda.net/hotelImages/237466/-1/3c1e3a1f8db11234771488667a99f6af.jpg?ca=13&ce=1&s=1024x768",
    "sourcePageUrl": "https://www.agoda.com/harmony-hotel/hotel/addis-ababa-et.html",
    "source": "official"
  },
  {
    "id": "fc7ab57d-fb13-4135-9e03-7fffc0521864",
    "name": "Hotel Lobelia",
    "imageUrl": "https://images.trvl-media.com/hotels/9000000/8260000/8257300/8257232/af0714b7.jpg",
    "sourcePageUrl": "https://images.trvl-media.com/hotels/9000000/8260000/8257300/8257232/af0714b7.jpg",
    "source": "official"
  },
  {
    "id": "acaabadc-7f2f-4923-b9e2-cd60628bde0b",
    "name": "Bole Ambassador Hotel",
    "imageUrl": "https://ik.imgkit.net/3vlqs5axxjf/external/https://media.iceportal.com/102413/photos/9378621_XL.jpg",
    "sourcePageUrl": "https://ik.imgkit.net/3vlqs5axxjf/external/https://media.iceportal.com/102413/photos/9378621_XL.jpg",
    "source": "official"
  },
  {
    "id": "aaa13088-bae5-48a0-8c4b-f2a46b1f8551",
    "name": "Moplaco Coffee Shop",
    "imageUrl": "https://typica.coffee/wp-content/uploads/2021/03/Moplaco-1-1024x683.jpg",
    "sourcePageUrl": "https://typica.coffee/wp-content/uploads/2021/03/Moplaco-1-1024x683.jpg",
    "source": "official"
  },
  {
    "id": "6fad0b58-712a-4e40-8326-f7bbb96927e2",
    "name": "Atikilt Tera vegetable market",
    "imageUrl": "https://commons.wikimedia.org/wiki/Special:FilePath/Addis_abeba,_mercato_sholla,_01.jpg",
    "sourcePageUrl": "https://commons.wikimedia.org/wiki/File:Addis_abeba,_mercato_sholla,_01.jpg",
    "source": "wikimedia"
  },
  {
    "id": "04400156-bfb9-43f9-9bf7-1034e0ddad96",
    "name": "Sabon Tera Market",
    "imageUrl": "https://commons.wikimedia.org/wiki/Special:FilePath/Addis_Mercato,_Adís_Abeba,_Etiopía,_2024-01-19,_DD_27.jpg",
    "sourcePageUrl": "https://commons.wikimedia.org/wiki/File:Addis_Mercato,_Adís_Abeba,_Etiopía,_2024-01-19,_DD_27.jpg",
    "source": "wikimedia"
  },
  {
    "id": "bbb32171-f4ee-4e7d-aeef-1f59cb81db22",
    "name": "Lucy Lounge",
    "imageUrl": "https://media-cdn.tripadvisor.com/media/photo-o/1e/81/dc/72/restaurant.jpg",
    "sourcePageUrl": "https://media-cdn.tripadvisor.com/media/photo-o/1e/81/dc/72/restaurant.jpg",
    "source": "official"
  },
  {
    "id": "91003df1-d60b-440d-baa0-3e7c35c9dcee",
    "name": "Five Loaves Restaurant",
    "imageUrl": "https://media-cdn.tripadvisor.com/media/photo-o/1a/0c/33/74/pesto-chicken-sandwich.jpg",
    "sourcePageUrl": "https://media-cdn.tripadvisor.com/media/photo-o/1a/0c/33/74/pesto-chicken-sandwich.jpg",
    "source": "official"
  },
  {
    "id": "57d8a146-0fda-412f-9ebc-994d8d3cb1d9",
    "name": "Dashen Traditional Restaurant",
    "imageUrl": "https://dynamic-media-cdn.tripadvisor.com/media/photo-o/15/4c/4f/aa/garden-terrace.jpg?w=1200&h=-1&s=1",
    "sourcePageUrl": "https://dynamic-media-cdn.tripadvisor.com/media/photo-o/15/4c/4f/aa/garden-terrace.jpg?w=1200&h=-1&s=1",
    "source": "official"
  },
  {
    "id": "c91e1910-878e-4bd5-8dc4-d00870fa0e10",
    "name": "Sishu Restaurant",
    "imageUrl": "https://media-cdn.tripadvisor.com/media/photo-o/11/0b/40/e3/the-original-home-made.jpg",
    "sourcePageUrl": "https://media-cdn.tripadvisor.com/media/photo-o/11/0b/40/e3/the-original-home-made.jpg",
    "source": "official"
  },
  {
    "id": "f2ee20ab-9727-4445-9ab9-325b2ba0a4ea",
    "name": "Habesha 2000",
    "imageUrl": "https://commons.wikimedia.org/wiki/Special:FilePath/Ethiopian_fasting_platter.jpg",
    "sourcePageUrl": "https://commons.wikimedia.org/wiki/File:Ethiopian_fasting_platter.jpg",
    "source": "wikimedia"
  },
  {
    "id": "85368033-8861-495e-8bef-c684b5e6ece3",
    "name": "2000 Habesha Cultural Restaurant",
    "imageUrl": "https://commons.wikimedia.org/wiki/Special:FilePath/Ethiopian_fasting_platter.jpg",
    "sourcePageUrl": "https://commons.wikimedia.org/wiki/File:Ethiopian_fasting_platter.jpg",
    "source": "wikimedia"
  },
  {
    "id": "91962938-38ba-469c-ae6d-7889d7d741d4",
    "name": "Addis City Highlights Tour",
    "imageUrl": "https://upload.wikimedia.org/wikipedia/commons/a/aa/ET-Addis_Abeba%2C_Churchill_Road.JPG",
    "sourcePageUrl": "https://commons.wikimedia.org/wiki/File:ET-Addis_Abeba,_Churchill_Road.JPG",
    "source": "wikimedia"
  },
  {
    "id": "311eb0dd-2691-4dbe-831a-bef6166180a0",
    "name": "Merkato Market Tour",
    "imageUrl": "https://commons.wikimedia.org/wiki/Special:FilePath/Addis_Mercato,_Adís_Abeba,_Etiopía,_2024-01-19,_DD_26.jpg",
    "sourcePageUrl": "https://commons.wikimedia.org/wiki/File:Addis_Mercato,_Adís_Abeba,_Etiopía,_2024-01-19,_DD_26.jpg",
    "source": "wikimedia"
  },
  {
    "id": "05269324-2f89-416b-9fda-831a60fa8923",
    "name": "Coffee Ceremony Experience",
    "imageUrl": "https://commons.wikimedia.org/wiki/Special:FilePath/Ethiopian_coffee_ceremony_-_Addis_Ababa.jpg",
    "sourcePageUrl": "https://commons.wikimedia.org/wiki/File:Ethiopian_coffee_ceremony_-_Addis_Ababa.jpg",
    "source": "wikimedia"
  },
  {
    "id": "1e9e4de8-9695-42cd-9c2f-2059cfa6711e",
    "name": "Entoto Mountain Tour",
    "imageUrl": "https://commons.wikimedia.org/wiki/Special:FilePath/Addis_Ababa_from_Entoto_Mountains.jpg",
    "sourcePageUrl": "https://commons.wikimedia.org/wiki/File:Addis_Ababa_from_Entoto_Mountains.jpg",
    "source": "wikimedia"
  },
  {
    "id": "05c48f7f-ff4d-47c6-9e34-c2288dd3fc17",
    "name": "Addis Food Tour",
    "imageUrl": "https://commons.wikimedia.org/wiki/Special:FilePath/Ethiopian_fasting_platter.jpg",
    "sourcePageUrl": "https://commons.wikimedia.org/wiki/File:Ethiopian_fasting_platter.jpg",
    "source": "wikimedia"
  },
  {
    "id": "70ca6741-8a47-4576-92ee-d3c926cdf277",
    "name": "Historical Addis Walking Tour",
    "imageUrl": "https://commons.wikimedia.org/wiki/Special:FilePath/Addis_Ababa_-_Piassa.jpg",
    "sourcePageUrl": "https://commons.wikimedia.org/wiki/File:Addis_Ababa_-_Piassa.jpg",
    "source": "wikimedia"
  },
  {
    "id": "a874eee5-b7c4-4bf6-af48-a540b850fab0",
    "name": "Unity Park Guided Tour",
    "imageUrl": "https://commons.wikimedia.org/wiki/Special:FilePath/Unity_Park_Addis_Ababa_Ethiopia_3.jpg",
    "sourcePageUrl": "https://commons.wikimedia.org/wiki/File:Unity_Park_Addis_Ababa_Ethiopia_3.jpg",
    "source": "wikimedia"
  },
  {
    "id": "09dab671-528d-4c5f-a620-4e8e9e826c04",
    "name": "Addis Nightlife Tour",
    "imageUrl": "https://commons.wikimedia.org/wiki/Special:FilePath/Addis_Ababa_at_the_night_time.jpg",
    "sourcePageUrl": "https://commons.wikimedia.org/wiki/File:Addis_Ababa_at_the_night_time.jpg",
    "source": "wikimedia"
  },
  {
    "id": "a17bcbd1-50fa-435c-ae7d-d520e12d94a2",
    "name": "Ride Ethiopia",
    "imageUrl": "https://ethiopianmonitor.com/wp-content/uploads/2020/01/images-2.jpg",
    "sourcePageUrl": "https://ethiopianmonitor.com/2020/01/30/ride-adds-new-tech-to-protect-drivers-their-cars/",
    "source": "blog"
  },
  {
    "id": "81b346e0-1f00-4030-9dd1-0fe270f20779",
    "name": "Feres Ride",
    "imageUrl": "https://pbs.twimg.com/media/FI_U_rXWYAs0h6O?format=jpg&name=large",
    "sourcePageUrl": "https://pbs.twimg.com/media/FI_U_rXWYAs0h6O?format=jpg&name=large",
    "source": "official"
  },
  {
    "id": "f21bb1b5-10de-4039-bb7e-fe9efb987ed8",
    "name": "ZayRide",
    "imageUrl": "https://www.zayride.com/images/logo.png",
    "sourcePageUrl": "https://www.zayride.com/",
    "source": "official"
  },
  {
    "id": "de48d1fb-fcba-4cc7-a67c-e33abc21b894",
    "name": "PickPick Taxi",
    "imageUrl": "https://modernaddis.com/wp-content/uploads/2021/09/57004832_810281565974338_3461867528907653120_n.jpg",
    "sourcePageUrl": "https://modernaddis.com/listings/pickpick-taxi/",
    "source": "official"
  },
  {
    "id": "fca5c18d-e7ae-4524-871d-beae0653aaee",
    "name": "Addis Airport Taxi",
    "imageUrl": "https://commons.wikimedia.org/wiki/Special:FilePath/Addis_Abeba_Taxis_(Sam_Effron).jpg",
    "sourcePageUrl": "https://commons.wikimedia.org/wiki/File:Addis_Abeba_Taxis_(Sam_Effron).jpg",
    "source": "wikimedia"
  },
  {
    "id": "7fb2df11-87ed-4b0d-87eb-c300b00076d2",
    "name": "ETT Tours Ethiopia",
    "imageUrl": "https://ethiotravelandtours.com/wp-content/uploads/2025/08/ETT-Logo-1.png",
    "sourcePageUrl": "https://ethiotravelandtours.com/",
    "source": "official"
  },
  {
    "id": "1a63c58c-f940-4b6c-b58c-f351b2ef4e26",
    "name": "Green Land Tours Ethiopia",
    "imageUrl": "https://www.safari-ethiopia.com/images/logos/logo.png",
    "sourcePageUrl": "https://www.safari-ethiopia.com/images/logos/logo.png",
    "source": "official"
  },
  {
    "id": "2a3a9df3-9808-4470-a1cc-67cca69eb7c3",
    "name": "Ethio Travel and Tours",
    "imageUrl": "https://ethiotravelandtours.com/wp-content/uploads/2021/08/ETT-Logo-1.png",
    "sourcePageUrl": "https://ethiotravelandtours.com/wp-content/uploads/2021/08/ETT-Logo-1.png",
    "source": "official"
  },
  {
    "id": "02eed363-7f82-43f8-a023-9d47b74f4ce9",
    "name": "Simien Eco Tours",
    "imageUrl": "https://b-cdn.springnest.com/media/img/z8/simienecotours_logo_horizontal_150dpide7e755.png",
    "sourcePageUrl": "https://www.simienecotours.com/",
    "source": "official"
  },
  {
    "id": "f5ac02f7-9166-48b7-b0d5-19fb7f198c4e",
    "name": "Travel Ethiopia",
    "imageUrl": "https://travelethiopia.com/images/logo-trans.png",
    "sourcePageUrl": "https://travelethiopia.com/",
    "source": "official"
  }
]